quickslurm/__init__.py
quickslurm/_version.py
quickslurm/data.py
quickslurm/quickslurm.py
quickslurm/utils.py
quickslurm-0.2.3.dist-info/METADATA
quickslurm-0.2.3.dist-info/WHEEL
quickslurm-0.2.3.dist-info/licenses/LICENSE
quickslurm-0.2.3.dist-info/RECORD
