Metadata-Version: 2.4
Name: quickslurm
Version: 0.2.3
Summary: A lightweight Python wrapper for Slurm sbatch/srun with robust subprocess handling and optional logging.
Project-URL: Homepage, https://github.com/quickslurm/quickslurm
Project-URL: Repository, https://github.com/quickslurm/quickslurm
Project-URL: Issues, https://github.com/quickslurm/quickslurm/issues
Author-email: Alex Buettner <alex.buettner93@gmail.com>, Jack Quimby <jack.quimby54@gmail.com>
License: MIT License
License-File: LICENSE
Keywords: cluster,hpc,quick,quickslurm,sbatch,slurm,srun,wrapper
Classifier: Development Status :: 4 - Beta
Classifier: Intended Audience :: Science/Research
Classifier: License :: OSI Approved :: MIT License
Classifier: Operating System :: OS Independent
Classifier: Programming Language :: Python
Classifier: Programming Language :: Python :: 3
Classifier: Programming Language :: Python :: 3 :: Only
Classifier: Programming Language :: Python :: 3.8
Classifier: Programming Language :: Python :: 3.9
Classifier: Programming Language :: Python :: 3.10
Classifier: Programming Language :: Python :: 3.11
Classifier: Programming Language :: Python :: 3.12
Classifier: Topic :: Scientific/Engineering
Classifier: Topic :: System :: Systems Administration
Requires-Python: >=3.8
Provides-Extra: docs
Requires-Dist: mkdocs; extra == 'docs'
Requires-Dist: mkdocs-include-markdown-plugin; extra == 'docs'
Requires-Dist: mkdocs-material; extra == 'docs'
Requires-Dist: mkdocstrings[python]; extra == 'docs'
Requires-Dist: pymdown-extensions; extra == 'docs'
Provides-Extra: test
Requires-Dist: pytest-cov>=4.0; extra == 'test'
Requires-Dist: pytest>=7.0; extra == 'test'
